horde_model_reference/__init__.py
horde_model_reference/_version.py
horde_model_reference/meta_consts.py
horde_model_reference/model_reference_manager.py
horde_model_reference/model_reference_metadata.py
horde_model_reference/model_reference_records.py
horde_model_reference/path_consts.py
horde_model_reference/py.typed
horde_model_reference/util.py
horde_model_reference/analytics/__init__.py
horde_model_reference/analytics/audit_analysis.py
horde_model_reference/analytics/audit_cache.py
horde_model_reference/analytics/base_cache.py
horde_model_reference/analytics/constants.py
horde_model_reference/analytics/filter_presets.py
horde_model_reference/analytics/statistics.py
horde_model_reference/analytics/statistics_cache.py
horde_model_reference/analytics/text_model_grouping.py
horde_model_reference/analytics/text_model_parser.py
horde_model_reference/backends/__init__.py
horde_model_reference/backends/base.py
horde_model_reference/backends/filesystem_backend.py
horde_model_reference/backends/github_backend.py
horde_model_reference/backends/http_backend.py
horde_model_reference/backends/redis_backend.py
horde_model_reference/backends/replica_backend_base.py
horde_model_reference/integrations/__init__.py
horde_model_reference/integrations/data_merger.py
horde_model_reference/integrations/horde_api_integration.py
horde_model_reference/integrations/horde_api_models.py
horde_model_reference/legacy/README.md
horde_model_reference/legacy/__init__.py
horde_model_reference/legacy/convert_all_legacy_dbs.py
horde_model_reference/legacy/text_csv_utils.py
horde_model_reference/legacy/validate_sd.py
horde_model_reference/legacy/classes/__init__.py
horde_model_reference/legacy/classes/legacy_converters.py
horde_model_reference/legacy/classes/legacy_models.py
horde_model_reference/service/__init__.py
horde_model_reference/service/app.py
horde_model_reference/service/shared.py
horde_model_reference/service/statistics/__init__.py
horde_model_reference-2.1.5.dist-info/licenses/LICENSE
horde_model_reference-2.1.5.dist-info/METADATA
horde_model_reference-2.1.5.dist-info/WHEEL
horde_model_reference-2.1.5.dist-info/entry_points.txt
horde_model_reference-2.1.5.dist-info/top_level.txt
horde_model_reference-2.1.5.dist-info/RECORD
