Metadata-Version: 2.4
Name: horde_model_reference
Version: 2.1.5
Summary: A helper library providing a way to work with the lists of generation models, utility models, and any other related files required for the AI-Horde ecosystem.
Author-email: tazlin <tazlin.on.github@gmail.com>, db0 <mail@dbzer0.com>
License:                     GNU AFFERO GENERAL PUBLIC LICENSE
Project-URL: Homepage, https://github.com/Haidra-Org/horde-model-reference
Classifier: Programming Language :: Python :: 3
Classifier: License :: OSI Approved :: GNU Affero General Public License v3
Classifier: Operating System :: OS Independent
Classifier: Development Status :: 4 - Beta
Requires-Python: >=3.10
License-File: LICENSE
Requires-Dist: aiofiles>=25.1.0
Requires-Dist: haidra-core>=0.0.5
Requires-Dist: httpx>=0.28.1
Requires-Dist: loguru>=0.7.3
Requires-Dist: mkdocs>=1.6.1
Requires-Dist: pydantic>=2.12.3
Requires-Dist: python-dotenv>=1.1.1
Requires-Dist: redis[hiredis]>=7.0.0
Requires-Dist: requests>=2.32.5
Requires-Dist: strenum>=0.4.15
Requires-Dist: typing-extensions>=4.15.0
Requires-Dist: ujson>=5.11.0
Provides-Extra: service
Requires-Dist: fastapi[standard]>=0.116.1; extra == "service"
Provides-Extra: sync
Requires-Dist: PyGithub>=2.5.0; extra == "sync"
Requires-Dist: gitpython>=3.1.0; extra == "sync"
Dynamic: license-file
